musae/__init__.py
musae-0.0.1.data/data/my_data/data_file
musae-0.0.1.dist-info/DESCRIPTION.rst
musae-0.0.1.dist-info/METADATA
musae-0.0.1.dist-info/RECORD
musae-0.0.1.dist-info/WHEEL
musae-0.0.1.dist-info/entry_points.txt
musae-0.0.1.dist-info/metadata.json
musae-0.0.1.dist-info/top_level.txt
