Metadata-Version: 2.0
Name: musae
Version: 0.0.1
Summary: A sample Python project
Home-page: https://github.com/thivaletde/musae.git
Author: Thierry Valet
Author-email: thivaletde@gmail.com
License: MIT
Keywords: sample setuptools development
Platform: UNKNOWN
Classifier: Development Status :: 3 - Alpha
Classifier: Intended Audience :: Developers
Classifier: Topic :: Software Development :: Build Tools
Classifier: License :: OSI Approved :: MIT License
Classifier: Programming Language :: Python :: 2
Classifier: Programming Language :: Python :: 2.7
